saildb/__init__.py
saildb-0.2.dist-info/METADATA
saildb-0.2.dist-info/WHEEL
saildb-0.2.dist-info/top_level.txt
saildb-0.2.dist-info/RECORD
