Metadata-Version: 2.1
Name: saildb
Version: 0.2
Summary: A high performing JSON alternative for speed and stability.
Home-page: https://github.com/Ow1e/SailDB
Author: Owen Shaule
Author-email: ow1e3@protonmail.com
License: UNKNOWN
Keywords: python,database
Platform: UNKNOWN
Classifier: Programming Language :: Python :: 3
Classifier: License :: OSI Approved :: MIT License
Classifier: Operating System :: OS Independent
